{
  "name": "Garrett Fowler",
  "age": 55,
  "address": {
    "street": "Uceuwu Grove",
    "city": "Versudeb",
    "state": "MS",
    "zip": "48989"
  },
  "contact": {
    "phone": "(335) 748-2901",
    "servicePhone": "800885995"
  },
  "birthday": "1975-07-29T06:57:50.486Z",
  "ip": "120.27.144.98",
  "foo": "bar",
  "profile": {
    "about": "Toc okpu ehupagto tihdum uro kiweztuj hirolwuf oto oza bufuci ruhjulje pa al hop nurodki usujifzid maob emo. Fivleze mu ahaburrun piwubo redikuf dij nebvik hoziclu manod jorebro fifa woew wuh buih rel hatdab. Pud ga sukve azniede ew odme codbuwsi kepdazok pivaac tokineh gige luilunu joloflu ewo raho ra kiutowe leefi. Hewa hevuvta uhober tac cafugfup gic usijagoc ob buno sadce vojdug zebsawgiz ahjiktu dagazowu. Ehu voaw kapumac capo ecosapime pahojgo daserew pubeg ah wajve bewju sigwulog. Sijalvar za buz idpicof fohbipi bohin fo et jazkanuw beim nacreji bezivefi raftiftod vuj telag gek ofezo. Pikri osu pev cekojafe kiveciju ujomalpu avbeez uwu dag cocpiz ca maru nenuna map iw irmu.",
    "bio": "Tub taju fiz did ika zum defouf rok oficezil cukji me giumne jog usmi uf subuva eguke. Ov gasivaha siare peawuso jeiw ibmeut bo mide wapa ecal je upvul detasuf vev oc lawa fi. Ufa befrovo jabele ca deztoc wov izahu ma ecdihsac cug dek cozesa."
  },
  "apiKey": "76d3c0fb77f9f78a2354f0aab59e6106c0d13aff1c0d0d7a987cf2508862e1a6",
  "currency": {
    "code": "CRC",
    "name": "Costa Rica Colon"
  }
}